LICENSE.md
MANIFEST.in
README.md
setup.cfg
setup.py
src/space/__init__.py
src/space/config.py
src/space/constants.py
src/space/env/__init__.py
src/space/env/moon.py
src/space/env/poleandtimes.py
src/space/env/sun.py
src/space/frames/__init__.py
src/space/frames/frame.py
src/space/frames/iau1980.py
src/space/frames/iau2010.py
src/space/frames/local.py
src/space/frames/data/tab5.1.txt
src/space/frames/data/tab5.2a.txt
src/space/frames/data/tab5.2b.txt
src/space/frames/data/tab5.2d.txt
src/space/orbits/__init__.py
src/space/orbits/ephem.py
src/space/orbits/forms.py
src/space/orbits/orbit.py
src/space/orbits/tle.py
src/space/propagators/__init__.py
src/space/propagators/sgp4.py
src/space/propagators/sgp4beta.py
src/space/utils/__init__.py
src/space/utils/date.py
src/space/utils/matrix.py
src/space/utils/memoize.py
src/space/utils/node.py
src/space/utils/units.py
src/space_api.egg-info/PKG-INFO
src/space_api.egg-info/SOURCES.txt
src/space_api.egg-info/dependency_links.txt
src/space_api.egg-info/namespace_packages.txt
src/space_api.egg-info/not-zip-safe
src/space_api.egg-info/requires.txt
src/space_api.egg-info/top_level.txt