Metadata-Version: 1.1
Name: space-api
Version: 0.2
Summary: Flight Dynamic Library
Home-page: UNKNOWN
Author: Jules David
Author-email: jules@onada.fr
License: GPLv3
Keywords: flight dynamic,satellite,space
Platform: any
Classifier: Development Status :: 2 - Pre-Alpha
Classifier: Intended Audience :: Science/Research
Classifier: License :: OSI Approved :: GNU General Public License v3 (GPLv3)
Classifier: Programming Language :: Python :: 3.5
Classifier: Programming Language :: Python :: 3.6
Classifier: Topic :: Scientific/Engineering :: Astronomy
Classifier: Topic :: Scientific/Engineering :: Physics
